LICENSE
MANIFEST.in
README.rst
setup.py
chembl_extras/__init__.py
chembl_extras/models.py
chembl_extras/moleculeFinder.py
chembl_extras/ontologies.py
chembl_extras/tests.py
chembl_extras.egg-info/PKG-INFO
chembl_extras.egg-info/SOURCES.txt
chembl_extras.egg-info/dependency_links.txt
chembl_extras.egg-info/not-zip-safe
chembl_extras.egg-info/requires.txt
chembl_extras.egg-info/top_level.txt
chembl_extras/management/__init__.py
chembl_extras/management/commands/__init__.py
chembl_extras/management/commands/activate_cartridge.py
chembl_extras/management/commands/cluster.py
chembl_extras/management/commands/create_blastdb.py
chembl_extras/management/commands/create_fasta.py
chembl_extras/management/commands/generate_backbone_models.py
chembl_extras/management/commands/generate_ora2pg_conf.py
chembl_extras/management/commands/mysyncdb.py
chembl_extras/management/commands/precache_charts.py
chembl_extras/management/commands/release_skeleton.py
chembl_extras/management/commands/sdf2fps.py
chembl_extras/management/commands/sdfexport.py
chembl_extras/management/commands/skeleton_resources.py