Metadata-Version: 1.1
Name: chembl-extras
Version: 0.8.1
Summary: Python package providing extra collection of django custom management commands for use with ChEMBL and some classes for use in future
Home-page: https://www.ebi.ac.uk/chembldb/index.php/ws
Author: Michal Nowotka
Author-email: mnowotka@ebi.ac.uk
License: Apache Software License
Platform: UNKNOWN
Classifier: Development Status :: 4 - Beta
Classifier: Environment :: Web Environment
Classifier: Framework :: Django
Classifier: Intended Audience :: Developers
Classifier: License :: OSI Approved :: Apache Software License
Classifier: Operating System :: POSIX :: Linux
Classifier: Programming Language :: Python :: 2.7
Classifier: Topic :: Scientific/Engineering :: Chemistry
